llm_logs_feedback.py
llm_logs_feedback-0.0.2.dist-info/LICENSE
llm_logs_feedback-0.0.2.dist-info/METADATA
llm_logs_feedback-0.0.2.dist-info/WHEEL
llm_logs_feedback-0.0.2.dist-info/entry_points.txt
llm_logs_feedback-0.0.2.dist-info/top_level.txt
llm_logs_feedback-0.0.2.dist-info/RECORD
