Metadata-Version: 2.2
Name: llm-logs-feedback
Version: 0.0.2
Summary: Feedback on LLM logs (prompts & response)
Author: Matthias Luebken
License: Apache-2.0
Project-URL: Homepage, https://github.com/luebken/llm-logs-feedback
Project-URL: Changelog, https://github.com/luebken/llm-logs-feedback/releases
Project-URL: Issues, https://github.com/luebken/llm-logs-feedback/issues
Project-URL: CI, https://github.com/luebken/llm-logs-feedback/actions
Classifier: License :: OSI Approved :: Apache Software License
Requires-Python: >=3.9
License-File: LICENSE
Requires-Dist: llm
Provides-Extra: test
Requires-Dist: pytest; extra == "test"
